<?xml version="1.0" encoding="utf-8"?>
<edmx:Edmx Version="1.0" xmlns:edmx="http://schemas.microsoft.com/ado/2007/06/edmx" xmlns:m="http://schemas.microsoft.com/ado/2007/08/dataservices/metadata" xmlns:sap="http://www.sap.com/Protocols/SAPData">
    <edmx:Reference Uri="./sap/opu/odata/iwfnd/catalogservice;v=2/Vocabularies(TechnicalName='%2FIWBEP%2FVOC_AGGREGATION',Version='0001',SAP__Origin='')/$value" xmlns:edmx="http://docs.oasis-open.org/odata/ns/edmx">
        <edmx:Include Namespace="Org.OData.Aggregation.V1" Alias="Aggregation"/>
    </edmx:Reference>
    <edmx:Reference Uri="./sap/opu/odata/iwfnd/catalogservice;v=2/Vocabularies(TechnicalName='%2FIWBEP%2FVOC_ANALYTICS',Version='0001',SAP__Origin='')/$value" xmlns:edmx="http://docs.oasis-open.org/odata/ns/edmx">
        <edmx:Include Namespace="com.sap.vocabularies.Analytics.v1" Alias="Analytics"/>
    </edmx:Reference>
    <edmx:Reference Uri="./sap/opu/odata/iwfnd/catalogservice;v=2/Vocabularies(TechnicalName='%2FIWBEP%2FVOC_CAPABILITIES',Version='0001',SAP__Origin='')/$value" xmlns:edmx="http://docs.oasis-open.org/odata/ns/edmx">
        <edmx:Include Namespace="Org.OData.Capabilities.V1" Alias="Capabilities"/>
    </edmx:Reference>
    <edmx:Reference Uri="./sap/opu/odata/iwfnd/catalogservice;v=2/Vocabularies(TechnicalName='%2FIWBEP%2FVOC_CODELIST',Version='0001',SAP__Origin='')/$value" xmlns:edmx="http://docs.oasis-open.org/odata/ns/edmx">
        <edmx:Include Namespace="com.sap.vocabularies.CodeList.v1" Alias="SAP__CodeList"/>
    </edmx:Reference>
    <edmx:Reference Uri="./sap/opu/odata/iwfnd/catalogservice;v=2/Vocabularies(TechnicalName='%2FIWBEP%2FVOC_COMMON',Version='0001',SAP__Origin='')/$value" xmlns:edmx="http://docs.oasis-open.org/odata/ns/edmx">
        <edmx:Include Namespace="com.sap.vocabularies.Common.v1" Alias="Common"/>
        <edmx:Include Namespace="com.sap.vocabularies.Common.v1" Alias="SAP__common"/>
    </edmx:Reference>
    <edmx:Reference Uri="./sap/opu/odata/iwfnd/catalogservice;v=2/Vocabularies(TechnicalName='%2FIWBEP%2FVOC_COMMUNICATION',Version='0001',SAP__Origin='')/$value" xmlns:edmx="http://docs.oasis-open.org/odata/ns/edmx">
        <edmx:Include Namespace="com.sap.vocabularies.Communication.v1" Alias="Communication"/>
    </edmx:Reference>
    <edmx:Reference Uri="./sap/opu/odata/iwfnd/catalogservice;v=2/Vocabularies(TechnicalName='%2FIWBEP%2FVOC_CORE',Version='0001',SAP__Origin='')/$value" xmlns:edmx="http://docs.oasis-open.org/odata/ns/edmx">
        <edmx:Include Namespace="Org.OData.Core.V1" Alias="SAP__core"/>
    </edmx:Reference>
    <edmx:Reference Uri="./sap/opu/odata/iwfnd/catalogservice;v=2/Vocabularies(TechnicalName='%2FIWBEP%2FVOC_MEASURES',Version='0001',SAP__Origin='')/$value" xmlns:edmx="http://docs.oasis-open.org/odata/ns/edmx">
        <edmx:Include Namespace="Org.OData.Measures.V1" Alias="Measures"/>
    </edmx:Reference>
    <edmx:Reference Uri="./sap/opu/odata/iwfnd/catalogservice;v=2/Vocabularies(TechnicalName='%2FIWBEP%2FVOC_PDF',Version='0001',SAP__Origin='')/$value" xmlns:edmx="http://docs.oasis-open.org/odata/ns/edmx">
        <edmx:Include Namespace="com.sap.vocabularies.PDF.v1" Alias="SAP__PDF"/>
    </edmx:Reference>
    <edmx:Reference Uri="./sap/opu/odata/iwfnd/catalogservice;v=2/Vocabularies(TechnicalName='%2FIWBEP%2FVOC_PERSONALDATA',Version='0001',SAP__Origin='')/$value" xmlns:edmx="http://docs.oasis-open.org/odata/ns/edmx">
        <edmx:Include Namespace="com.sap.vocabularies.PersonalData.v1" Alias="PersonalData"/>
    </edmx:Reference>
    <edmx:Reference Uri="./sap/opu/odata/iwfnd/catalogservice;v=2/Vocabularies(TechnicalName='%2FIWBEP%2FVOC_UI',Version='0001',SAP__Origin='')/$value" xmlns:edmx="http://docs.oasis-open.org/odata/ns/edmx">
        <edmx:Include Namespace="com.sap.vocabularies.UI.v1" Alias="UI"/>
    </edmx:Reference>
    <edmx:Reference Uri="./sap/opu/odata/iwfnd/catalogservice;v=2/Vocabularies(TechnicalName='%2FIWBEP%2FVOC_VALIDATION',Version='0001',SAP__Origin='')/$value" xmlns:edmx="http://docs.oasis-open.org/odata/ns/edmx">
        <edmx:Include Namespace="Org.OData.Validation.V1" Alias="Validation"/>
    </edmx:Reference>
    <edmx:DataServices m:DataServiceVersion="2.0">
        <Schema Namespace="cds_xsmyxpatient_ov_sdef" xml:lang="en" sap:schema-version="1" xmlns="http://schemas.microsoft.com/ado/2008/09/edm">
            <EntityType Name="xSMYxC_CASE_OVType" sap:label="Episode Of Care Set" sap:content-version="1">
                <Key>
                    <PropertyRef Name="CaseUUID"/>
                </Key>
                <Property Name="CaseUUID" Type="Edm.Guid" Nullable="false" sap:label="Case UUID" sap:creatable="false" sap:updatable="false"/>
                <Property Name="PatientID" Type="Edm.String" MaxLength="10" sap:display-format="UpperCase" sap:label="Patient ID" sap:creatable="false" sap:updatable="false"/>
                <Property Name="PatientUuid" Type="Edm.Guid" Nullable="false" sap:label="Patient UUID" sap:updatable="false"/>
                <Property Name="CaseID" Type="Edm.String" MaxLength="12" sap:display-format="UpperCase" sap:label="Case ID" sap:creatable="false" sap:updatable="false"/>
                <Property Name="CaseStatus" Type="Edm.String" MaxLength="1" sap:display-format="UpperCase" sap:label="Status" sap:quickinfo="Case Status"/>
                <Property Name="CaseType" Type="Edm.String" MaxLength="2" sap:display-format="UpperCase" sap:label="Total Paid Amount" sap:quickinfo="Case Type"/>
                <Property Name="CaseCat" Type="Edm.String" MaxLength="2" sap:display-format="UpperCase" sap:label="Case Category"/>
                <Property Name="BillStat" Type="Edm.String" MaxLength="1" sap:display-format="UpperCase" sap:label="Episode Type" sap:quickinfo="Billing Status"/>
                <Property Name="Org" Type="Edm.String" Nullable="false" MaxLength="8" sap:display-format="UpperCase" sap:label="Healthcare Facility" sap:quickinfo="Organization (Institution)" sap:updatable="false"/>
                <Property Name="QuickFlag" Type="Edm.Boolean" sap:label="Primary Diagnosis" sap:quickinfo="Quick Registration flag"/>
                <Property Name="CaseStart" Type="Edm.DateTimeOffset" Precision="0" sap:label="Start Date and Time" sap:quickinfo="Case Start Date and Time"/>
                <Property Name="CaseEnd" Type="Edm.DateTimeOffset" Precision="0" sap:label="End date and Time" sap:quickinfo="Case End Date and Time"/>
                <Property Name="HealthUUID" Type="Edm.Guid" sap:label="Health Problem UUID"/>
                <Property Name="CreatedBy" Type="Edm.String" MaxLength="12" sap:display-format="UpperCase" sap:label="Created By" sap:quickinfo="Created By User" sap:creatable="false" sap:updatable="false"/>
                <Property Name="CreatedAt" Type="Edm.DateTimeOffset" Precision="7" sap:label="Date Range" sap:quickinfo="Creation Date Time" sap:creatable="false" sap:updatable="false"/>
                <Property Name="LastChangedBy" Type="Edm.String" MaxLength="12" sap:display-format="UpperCase" sap:label="Changed By" sap:quickinfo="Last Changed By User" sap:creatable="false" sap:updatable="false"/>
                <Property Name="LastChangedAt" Type="Edm.DateTimeOffset" Precision="7" sap:label="Changed On" sap:quickinfo="Last Change Date Time" sap:creatable="false" sap:updatable="false"/>
                <Property Name="LocalLastChangedAt" Type="Edm.DateTimeOffset" Precision="7" sap:label="Changed On" sap:quickinfo="Local Instance Last Change Date Time" sap:creatable="false" sap:updatable="false"/>
                <Property Name="Canceled" Type="Edm.Boolean" sap:label="Outstanding Balance" sap:quickinfo="Canceled Flag"/>
                <Property Name="BusinessPartnerUUID" Type="Edm.Guid" sap:label="Total Billed Amount" sap:quickinfo="Business Partner UUID"/>
                <Property Name="BirthDate" Type="Edm.DateTime" Precision="0" sap:display-format="Date" sap:label="Date of Birth" sap:quickinfo="Date of Birth of Business Partner" sap:creatable="false" sap:updatable="false"/>
                <Property Name="FirstName" Type="Edm.String" MaxLength="40" sap:label="First Name" sap:quickinfo="First Name of Business Partner (Person)" sap:creatable="false" sap:updatable="false"/>
                <Property Name="EmpId" Type="Edm.String" MaxLength="12" sap:display-format="UpperCase" sap:label="Episode ID" sap:quickinfo="Encounter ID"/>
                <NavigationProperty Name="to_Encounter" Relationship="cds_xsmyxpatient_ov_sdef.assoc_0D98C2FA7528CA7C3FA6A6250EF6821D" FromRole="FromRole_assoc_0D98C2FA7528CA7C3FA6A6250EF6821D" ToRole="ToRole_assoc_0D98C2FA7528CA7C3FA6A6250EF6821D"/>
                <NavigationProperty Name="to_Patient" Relationship="cds_xsmyxpatient_ov_sdef.assoc_F75C82D5E58129306E7348D48D16160E" FromRole="FromRole_assoc_F75C82D5E58129306E7348D48D16160E" ToRole="ToRole_assoc_F75C82D5E58129306E7348D48D16160E"/>
            </EntityType>
            <EntityType Name="xSMYxC_ENCOUNTER_OVType" sap:label="Encounters" sap:content-version="1">
                <Key>
                    <PropertyRef Name="EncounterUUID"/>
                </Key>
                <Property Name="EncounterUUID" Type="Edm.Guid" Nullable="false" sap:label="Encounter UUID" sap:creatable="false" sap:updatable="false"/>
                <Property Name="CaseUUID" Type="Edm.Guid" Nullable="false" sap:label="Case UUID" sap:updatable="false"/>
                <Property Name="EncID" Type="Edm.String" MaxLength="12" sap:display-format="UpperCase" sap:label="Encounter ID" sap:creatable="false" sap:updatable="false"/>
                <Property Name="EncStatus" Type="Edm.String" MaxLength="2" sap:display-format="UpperCase" sap:label="Status" sap:quickinfo="External Encounter Status"/>
                <Property Name="EncClass" Type="Edm.String" MaxLength="2" sap:display-format="UpperCase" sap:label="External Enc. Class" sap:quickinfo="External Encounter Class"/>
                <Property Name="EncPrio" Type="Edm.String" MaxLength="2" sap:display-format="UpperCase" sap:label="Encounter Priority"/>
                <Property Name="EncType" Type="Edm.String" MaxLength="2" sap:display-format="UpperCase" sap:label="Encounters Type" sap:quickinfo="Encounter Type"/>
                <Property Name="EncStart" Type="Edm.DateTimeOffset" Precision="0" sap:label="Date of Encounter" sap:quickinfo="Encounter Start Date and Time" sap:semantics="duration"/>
                <Property Name="EncEnd" Type="Edm.DateTimeOffset" Precision="0" sap:label="End Date and Time" sap:quickinfo="Encounter End Date and Time"/>
                <Property Name="ApptUUID" Type="Edm.Guid" sap:label="Appointment UUID"/>
                <Property Name="CreatedBy" Type="Edm.String" MaxLength="12" sap:display-format="UpperCase" sap:label="Created By" sap:quickinfo="Created By User" sap:creatable="false" sap:updatable="false"/>
                <Property Name="CreatedAt" Type="Edm.DateTimeOffset" Precision="7" sap:label="Created On" sap:quickinfo="Creation Date Time" sap:creatable="false" sap:updatable="false"/>
                <Property Name="LastChangedBy" Type="Edm.String" MaxLength="12" sap:display-format="UpperCase" sap:label="Changed By" sap:quickinfo="Last Changed By User" sap:creatable="false" sap:updatable="false"/>
                <Property Name="LastChangedAt" Type="Edm.DateTimeOffset" Precision="7" sap:label="Changed On" sap:quickinfo="Last Change Date Time" sap:creatable="false" sap:updatable="false"/>
                <Property Name="LocalLastChangedAt" Type="Edm.DateTimeOffset" Precision="7" sap:label="Changed On" sap:quickinfo="Local Instance Last Change Date Time" sap:creatable="false" sap:updatable="false"/>
                <Property Name="Canceled" Type="Edm.Boolean" sap:label="Canceled" sap:quickinfo="Canceled Flag" sap:creatable="false" sap:updatable="false"/>
                <Property Name="OrgUnit" Type="Edm.String" MaxLength="10" sap:display-format="UpperCase" sap:label="Organizational Unit" sap:heading="" sap:creatable="false" sap:updatable="false"/>
                <Property Name="TreatUnit" Type="Edm.String" MaxLength="10" sap:display-format="UpperCase" sap:label="Treatment Unit" sap:creatable="false" sap:updatable="false"/>
                <Property Name="Room" Type="Edm.String" MaxLength="10" sap:label="Room" sap:creatable="false" sap:updatable="false"/>
                <Property Name="Bed" Type="Edm.String" MaxLength="10" sap:label="Bed" sap:creatable="false" sap:updatable="false"/>
                <Property Name="EncTypeInt" Type="Edm.String" MaxLength="2" sap:display-format="UpperCase" sap:label="Enc. Type Internal" sap:quickinfo="Encounter Type Internal" sap:creatable="false" sap:updatable="false"/>
                <NavigationProperty Name="to_EpisodeOfCare" Relationship="cds_xsmyxpatient_ov_sdef.assoc_EFA97A370DEF41CC75A0D63A288559AF" FromRole="FromRole_assoc_EFA97A370DEF41CC75A0D63A288559AF" ToRole="ToRole_assoc_EFA97A370DEF41CC75A0D63A288559AF"/>
            </EntityType>
            <EntityType Name="xSMYxC_PATIENT_OVType" sap:label="Patients" sap:content-version="1">
                <Key>
                    <PropertyRef Name="PatientId"/>
                </Key>
                <Property Name="Update_mc" Type="Edm.Boolean" sap:label="Dyn. Method Control" sap:creatable="false" sap:updatable="false" sap:sortable="false" sap:filterable="false"/>
                <Property Name="PatientId" Type="Edm.String" Nullable="false" MaxLength="10" sap:display-format="UpperCase" sap:label="Patient ID" sap:creatable="false" sap:updatable="false"/>
                <Property Name="BusinessPartnerUUID" Type="Edm.Guid" sap:label="Total Billed Amount" sap:quickinfo="Business Partner UUID" sap:creatable="false" sap:updatable="false"/>
                <Property Name="PatientUUID" Type="Edm.Guid" sap:label="Patient UUID" sap:updatable="false"/>
                <Property Name="Inactive" Type="Edm.Boolean" sap:label="Inactive" sap:quickinfo="Patient is inactive"/>
                <Property Name="CreatedBy" Type="Edm.String" MaxLength="12" sap:display-format="UpperCase" sap:label="Created By" sap:quickinfo="Created By User" sap:creatable="false" sap:updatable="false"/>
                <Property Name="CreatedAt" Type="Edm.DateTimeOffset" Precision="7" sap:label="Date Range" sap:quickinfo="Creation Date Time" sap:creatable="false" sap:updatable="false"/>
                <Property Name="LastChangedBy" Type="Edm.String" MaxLength="12" sap:display-format="UpperCase" sap:label="Changed By" sap:quickinfo="Last Changed By User" sap:creatable="false" sap:updatable="false"/>
                <Property Name="LastChangedAt" Type="Edm.DateTimeOffset" Precision="7" sap:label="Changed On" sap:quickinfo="Last Change Date Time" sap:creatable="false" sap:updatable="false"/>
                <Property Name="LocalLastChangedAt" Type="Edm.DateTimeOffset" Precision="7" sap:label="Changed On" sap:quickinfo="Local Instance Last Change Date Time" sap:creatable="false" sap:updatable="false"/>
                <Property Name="FirstName" Type="Edm.String" MaxLength="40" sap:label="Partner Name" sap:quickinfo="First Name of Business Partner (Person)"/>
                <Property Name="BirthDate" Type="Edm.DateTime" Precision="0" sap:display-format="Date" sap:label="Date of Birth" sap:quickinfo="Date of Birth of Business Partner"/>
                <Property Name="Org" Type="Edm.String" MaxLength="40" sap:label="Organization" sap:quickinfo="Name 1 of organization"/>
                <Property Name="EmpId" Type="Edm.String" MaxLength="12" sap:display-format="UpperCase" sap:label="Episode ID" sap:quickinfo="Encounter ID"/>
                <NavigationProperty Name="to_Case" Relationship="cds_xsmyxpatient_ov_sdef.assoc_F1133A265B568B0CA18E38A117B7F811" FromRole="FromRole_assoc_F1133A265B568B0CA18E38A117B7F811" ToRole="ToRole_assoc_F1133A265B568B0CA18E38A117B7F811"/>
                <NavigationProperty Name="to_Encounter" Relationship="cds_xsmyxpatient_ov_sdef.assoc_45353E7458BEC3091C0CB247DFD6E58E" FromRole="FromRole_assoc_45353E7458BEC3091C0CB247DFD6E58E" ToRole="ToRole_assoc_45353E7458BEC3091C0CB247DFD6E58E"/>
            </EntityType>
            <EntityType Name="SAP__Currency" sap:content-version="1">
                <Key>
                    <PropertyRef Name="CurrencyCode"/>
                </Key>
                <Property Name="CurrencyCode" Type="Edm.String" Nullable="false" MaxLength="5" sap:label="Currency" sap:semantics="currency-code"/>
                <Property Name="ISOCode" Type="Edm.String" Nullable="false" MaxLength="3" sap:label="ISO code"/>
                <Property Name="Text" Type="Edm.String" Nullable="false" MaxLength="15" sap:label="Short text"/>
                <Property Name="DecimalPlaces" Type="Edm.Byte" Nullable="false" sap:label="Decimals"/>
            </EntityType>
            <EntityType Name="SAP__UnitOfMeasure" sap:content-version="1">
                <Key>
                    <PropertyRef Name="UnitCode"/>
                </Key>
                <Property Name="UnitCode" Type="Edm.String" Nullable="false" MaxLength="3" sap:label="Internal UoM" sap:semantics="unit-of-measure"/>
                <Property Name="ISOCode" Type="Edm.String" Nullable="false" MaxLength="3" sap:label="ISO Code"/>
                <Property Name="ExternalCode" Type="Edm.String" Nullable="false" MaxLength="3" sap:label="Commercial"/>
                <Property Name="Text" Type="Edm.String" Nullable="false" MaxLength="30" sap:label="Meas. Unit Text"/>
                <Property Name="DecimalPlaces" Type="Edm.Int16" sap:label="Decimal Places"/>
            </EntityType>
            <EntityType Name="SAP__DocumentDescription" sap:content-version="1">
                <Key>
                    <PropertyRef Name="Id"/>
                </Key>
                <Property Name="Id" Type="Edm.Guid" Nullable="false" sap:label="UUID"/>
                <Property Name="CreatedBy" Type="Edm.String" Nullable="false" MaxLength="12"/>
                <Property Name="CreatedAt" Type="Edm.DateTime" Nullable="false" Precision="0" sap:label="Time Stamp"/>
                <Property Name="FileName" Type="Edm.String" Nullable="false" MaxLength="256"/>
                <Property Name="Title" Type="Edm.String" Nullable="false" MaxLength="256"/>
                <NavigationProperty Name="Format" Relationship="cds_xsmyxpatient_ov_sdef.to_format" FromRole="FromRole_to_format" ToRole="ToRole_to_format"/>
                <NavigationProperty Name="TableColumns" Relationship="cds_xsmyxpatient_ov_sdef.to_tablecolumns" FromRole="FromRole_to_tablecolumns" ToRole="ToRole_to_tablecolumns"/>
                <NavigationProperty Name="CoverPage" Relationship="cds_xsmyxpatient_ov_sdef.to_coverpage" FromRole="FromRole_to_coverpage" ToRole="ToRole_to_coverpage"/>
                <NavigationProperty Name="Signature" Relationship="cds_xsmyxpatient_ov_sdef.to_signature" FromRole="FromRole_to_signature" ToRole="ToRole_to_signature"/>
                <NavigationProperty Name="PDFStandard" Relationship="cds_xsmyxpatient_ov_sdef.to_pdfstandard" FromRole="FromRole_to_pdfstandard" ToRole="ToRole_to_pdfstandard"/>
                <NavigationProperty Name="Hierarchy" Relationship="cds_xsmyxpatient_ov_sdef.to_Hierarchy" FromRole="FromRole_to_Hierarchy" ToRole="ToRole_to_Hierarchy"/>
                <NavigationProperty Name="Header" Relationship="cds_xsmyxpatient_ov_sdef.to_header" FromRole="FromRole_to_header" ToRole="ToRole_to_header"/>
                <NavigationProperty Name="Footer" Relationship="cds_xsmyxpatient_ov_sdef.to_Footer" FromRole="FromRole_to_Footer" ToRole="ToRole_to_Footer"/>
            </EntityType>
            <EntityType Name="SAP__Format" sap:content-version="1">
                <Key>
                    <PropertyRef Name="Id"/>
                </Key>
                <Property Name="FitToPage" Type="cds_xsmyxpatient_ov_sdef.SAP__FitToPage" Nullable="false"/>
                <Property Name="Id" Type="Edm.Guid" Nullable="false" sap:label="UUID" sap:creatable="false" sap:updatable="false" sap:sortable="false" sap:filterable="false"/>
                <Property Name="FontSize" Type="Edm.Int32" Nullable="false" sap:creatable="false" sap:updatable="false" sap:sortable="false" sap:filterable="false"/>
                <Property Name="Orientation" Type="Edm.String" Nullable="false" MaxLength="10" sap:creatable="false" sap:updatable="false" sap:sortable="false" sap:filterable="false"/>
                <Property Name="PaperSize" Type="Edm.String" Nullable="false" MaxLength="10" sap:creatable="false" sap:updatable="false" sap:sortable="false" sap:filterable="false"/>
                <Property Name="BorderSize" Type="Edm.Int32" Nullable="false" sap:creatable="false" sap:updatable="false" sap:sortable="false" sap:filterable="false"/>
                <Property Name="MarginSize" Type="Edm.Int32" Nullable="false" sap:creatable="false" sap:updatable="false" sap:sortable="false" sap:filterable="false"/>
                <Property Name="FontName" Type="Edm.String" Nullable="false" MaxLength="255" sap:label="Font Name" sap:creatable="false" sap:updatable="false" sap:sortable="false" sap:filterable="false"/>
                <Property Name="Padding" Type="Edm.Int32" Nullable="false" sap:creatable="false" sap:updatable="false" sap:sortable="false" sap:filterable="false"/>
            </EntityType>
            <EntityType Name="SAP__PDFStandard" sap:content-version="1">
                <Key>
                    <PropertyRef Name="Id"/>
                </Key>
                <Property Name="Id" Type="Edm.Guid" Nullable="false" sap:label="UUID" sap:creatable="false" sap:updatable="false" sap:sortable="false" sap:filterable="false"/>
                <Property Name="UsePDFAConformance" Type="Edm.Boolean" Nullable="false" sap:creatable="false" sap:updatable="false" sap:sortable="false" sap:filterable="false"/>
                <Property Name="DoEnableAccessibility" Type="Edm.Boolean" Nullable="false" sap:label="Indicator" sap:creatable="false" sap:updatable="false" sap:sortable="false" sap:filterable="false"/>
            </EntityType>
            <EntityType Name="SAP__TableColumns" sap:content-version="1">
                <Key>
                    <PropertyRef Name="Id"/>
                    <PropertyRef Name="Name"/>
                    <PropertyRef Name="Header"/>
                </Key>
                <Property Name="Id" Type="Edm.Guid" Nullable="false" sap:label="UUID" sap:creatable="false" sap:updatable="false" sap:sortable="false" sap:filterable="false"/>
                <Property Name="Name" Type="Edm.String" Nullable="false" MaxLength="256" sap:creatable="false" sap:updatable="false" sap:sortable="false" sap:filterable="false"/>
                <Property Name="Header" Type="Edm.String" Nullable="false" MaxLength="256" sap:creatable="false" sap:updatable="false" sap:sortable="false" sap:filterable="false"/>
                <Property Name="HorizontalAlignment" Type="Edm.String" Nullable="false" MaxLength="10" sap:creatable="false" sap:updatable="false" sap:sortable="false" sap:filterable="false"/>
            </EntityType>
            <EntityType Name="SAP__CoverPage" sap:content-version="1">
                <Key>
                    <PropertyRef Name="Title"/>
                    <PropertyRef Name="Id"/>
                    <PropertyRef Name="Name"/>
                </Key>
                <Property Name="Title" Type="Edm.String" Nullable="false" MaxLength="256" sap:creatable="false" sap:updatable="false" sap:sortable="false" sap:filterable="false"/>
                <Property Name="Id" Type="Edm.Guid" Nullable="false" sap:label="UUID" sap:creatable="false" sap:updatable="false" sap:sortable="false" sap:filterable="false"/>
                <Property Name="Name" Type="Edm.String" Nullable="false" MaxLength="256" sap:creatable="false" sap:updatable="false" sap:sortable="false" sap:filterable="false"/>
                <Property Name="Value" Type="Edm.String" Nullable="false" MaxLength="256" sap:creatable="false" sap:updatable="false" sap:sortable="false" sap:filterable="false"/>
            </EntityType>
            <EntityType Name="SAP__Signature" sap:content-version="1">
                <Key>
                    <PropertyRef Name="Id"/>
                </Key>
                <Property Name="Id" Type="Edm.Guid" Nullable="false" sap:label="UUID" sap:creatable="false" sap:updatable="false" sap:sortable="false" sap:filterable="false"/>
                <Property Name="DoSign" Type="Edm.Boolean" Nullable="false" sap:label="Indicator" sap:creatable="false" sap:updatable="false" sap:sortable="false" sap:filterable="false"/>
                <Property Name="Reason" Type="Edm.String" Nullable="false" MaxLength="256" sap:creatable="false" sap:updatable="false" sap:sortable="false" sap:filterable="false"/>
            </EntityType>
            <EntityType Name="SAP__Hierarchy" sap:content-version="1">
                <Key>
                    <PropertyRef Name="Id"/>
                </Key>
                <Property Name="Id" Type="Edm.Guid" Nullable="false" sap:label="UUID" sap:creatable="false" sap:updatable="false" sap:sortable="false" sap:filterable="false"/>
                <Property Name="DistanceFromRootElement" Type="Edm.String" Nullable="false" MaxLength="256" sap:creatable="false" sap:updatable="false" sap:sortable="false" sap:filterable="false"/>
                <Property Name="DrillStateElement" Type="Edm.String" Nullable="false" MaxLength="256" sap:creatable="false" sap:updatable="false" sap:sortable="false" sap:filterable="false"/>
            </EntityType>
            <EntityType Name="SAP__PDFHeader" sap:content-version="1">
                <Key>
                    <PropertyRef Name="Id"/>
                </Key>
                <Property Name="Right" Type="cds_xsmyxpatient_ov_sdef.SAP__HeaderFooterField" Nullable="false"/>
                <Property Name="Left" Type="cds_xsmyxpatient_ov_sdef.SAP__HeaderFooterField" Nullable="false"/>
                <Property Name="Center" Type="cds_xsmyxpatient_ov_sdef.SAP__HeaderFooterField" Nullable="false"/>
                <Property Name="Id" Type="Edm.Guid" Nullable="false" sap:label="UUID" sap:creatable="false" sap:updatable="false" sap:sortable="false" sap:filterable="false"/>
            </EntityType>
            <EntityType Name="SAP__PDFFooter" sap:content-version="1">
                <Key>
                    <PropertyRef Name="Id"/>
                </Key>
                <Property Name="Right" Type="cds_xsmyxpatient_ov_sdef.SAP__HeaderFooterField" Nullable="false"/>
                <Property Name="Left" Type="cds_xsmyxpatient_ov_sdef.SAP__HeaderFooterField" Nullable="false"/>
                <Property Name="Center" Type="cds_xsmyxpatient_ov_sdef.SAP__HeaderFooterField" Nullable="false"/>
                <Property Name="Id" Type="Edm.Guid" Nullable="false" sap:label="UUID" sap:creatable="false" sap:updatable="false" sap:sortable="false" sap:filterable="false"/>
            </EntityType>
            <EntityType Name="SAP__ValueHelp" sap:content-version="1">
                <Key>
                    <PropertyRef Name="VALUEHELP"/>
                </Key>
                <Property Name="VALUEHELP" Type="Edm.String" Nullable="false"/>
                <Property Name="FIELD_VALUE" Type="Edm.String" Nullable="false" MaxLength="10"/>
                <Property Name="DESCRIPTION" Type="Edm.String"/>
            </EntityType>
            <ComplexType Name="SAP__FitToPage">
                <Property Name="ErrorRecoveryBehavior" Type="Edm.String" Nullable="false" MaxLength="8" sap:label="Error behavior" sap:creatable="false" sap:updatable="false" sap:sortable="false" sap:filterable="false"/>
                <Property Name="IsEnabled" Type="Edm.Boolean" Nullable="false" sap:creatable="false" sap:updatable="false" sap:sortable="false" sap:filterable="false"/>
                <Property Name="MinimumFontSize" Type="Edm.Int32" Nullable="false" sap:creatable="false" sap:updatable="false" sap:sortable="false" sap:filterable="false"/>
            </ComplexType>
            <ComplexType Name="SAP__HeaderFooterField">
                <Property Name="Type" Type="Edm.String" Nullable="false" MaxLength="256" sap:creatable="false" sap:updatable="false" sap:sortable="false" sap:filterable="false"/>
            </ComplexType>
            <Association Name="assoc_F1133A265B568B0CA18E38A117B7F811" sap:content-version="1">
                <End Type="cds_xsmyxpatient_ov_sdef.xSMYxC_PATIENT_OVType" Multiplicity="1" Role="FromRole_assoc_F1133A265B568B0CA18E38A117B7F811"/>
                <End Type="cds_xsmyxpatient_ov_sdef.xSMYxC_CASE_OVType" Multiplicity="*" Role="ToRole_assoc_F1133A265B568B0CA18E38A117B7F811"/>
            </Association>
            <Association Name="assoc_45353E7458BEC3091C0CB247DFD6E58E" sap:content-version="1">
                <End Type="cds_xsmyxpatient_ov_sdef.xSMYxC_PATIENT_OVType" Multiplicity="1" Role="FromRole_assoc_45353E7458BEC3091C0CB247DFD6E58E"/>
                <End Type="cds_xsmyxpatient_ov_sdef.xSMYxC_ENCOUNTER_OVType" Multiplicity="*" Role="ToRole_assoc_45353E7458BEC3091C0CB247DFD6E58E"/>
            </Association>
            <Association Name="to_format" sap:content-version="1">
                <End Type="cds_xsmyxpatient_ov_sdef.SAP__DocumentDescription" Multiplicity="1" Role="FromRole_to_format"/>
                <End Type="cds_xsmyxpatient_ov_sdef.SAP__Format" Multiplicity="1" Role="ToRole_to_format"/>
                <ReferentialConstraint>
                    <Principal Role="FromRole_to_format">
                        <PropertyRef Name="Id"/>
                    </Principal>
                    <Dependent Role="ToRole_to_format">
                        <PropertyRef Name="Id"/>
                    </Dependent>
                </ReferentialConstraint>
            </Association>
            <Association Name="to_tablecolumns" sap:content-version="1">
                <End Type="cds_xsmyxpatient_ov_sdef.SAP__DocumentDescription" Multiplicity="1" Role="FromRole_to_tablecolumns"/>
                <End Type="cds_xsmyxpatient_ov_sdef.SAP__TableColumns" Multiplicity="*" Role="ToRole_to_tablecolumns"/>
                <ReferentialConstraint>
                    <Principal Role="FromRole_to_tablecolumns">
                        <PropertyRef Name="Id"/>
                    </Principal>
                    <Dependent Role="ToRole_to_tablecolumns">
                        <PropertyRef Name="Id"/>
                    </Dependent>
                </ReferentialConstraint>
            </Association>
            <Association Name="to_coverpage" sap:content-version="1">
                <End Type="cds_xsmyxpatient_ov_sdef.SAP__DocumentDescription" Multiplicity="1" Role="FromRole_to_coverpage"/>
                <End Type="cds_xsmyxpatient_ov_sdef.SAP__CoverPage" Multiplicity="*" Role="ToRole_to_coverpage"/>
                <ReferentialConstraint>
                    <Principal Role="FromRole_to_coverpage">
                        <PropertyRef Name="Id"/>
                    </Principal>
                    <Dependent Role="ToRole_to_coverpage">
                        <PropertyRef Name="Id"/>
                    </Dependent>
                </ReferentialConstraint>
            </Association>
            <Association Name="to_signature" sap:content-version="1">
                <End Type="cds_xsmyxpatient_ov_sdef.SAP__DocumentDescription" Multiplicity="1" Role="FromRole_to_signature"/>
                <End Type="cds_xsmyxpatient_ov_sdef.SAP__Signature" Multiplicity="1" Role="ToRole_to_signature"/>
                <ReferentialConstraint>
                    <Principal Role="FromRole_to_signature">
                        <PropertyRef Name="Id"/>
                    </Principal>
                    <Dependent Role="ToRole_to_signature">
                        <PropertyRef Name="Id"/>
                    </Dependent>
                </ReferentialConstraint>
            </Association>
            <Association Name="to_pdfstandard" sap:content-version="1">
                <End Type="cds_xsmyxpatient_ov_sdef.SAP__DocumentDescription" Multiplicity="1" Role="FromRole_to_pdfstandard"/>
                <End Type="cds_xsmyxpatient_ov_sdef.SAP__PDFStandard" Multiplicity="1" Role="ToRole_to_pdfstandard"/>
                <ReferentialConstraint>
                    <Principal Role="FromRole_to_pdfstandard">
                        <PropertyRef Name="Id"/>
                    </Principal>
                    <Dependent Role="ToRole_to_pdfstandard">
                        <PropertyRef Name="Id"/>
                    </Dependent>
                </ReferentialConstraint>
            </Association>
            <Association Name="to_Hierarchy" sap:content-version="1">
                <End Type="cds_xsmyxpatient_ov_sdef.SAP__DocumentDescription" Multiplicity="1" Role="FromRole_to_Hierarchy"/>
                <End Type="cds_xsmyxpatient_ov_sdef.SAP__Hierarchy" Multiplicity="1" Role="ToRole_to_Hierarchy"/>
                <ReferentialConstraint>
                    <Principal Role="FromRole_to_Hierarchy">
                        <PropertyRef Name="Id"/>
                    </Principal>
                    <Dependent Role="ToRole_to_Hierarchy">
                        <PropertyRef Name="Id"/>
                    </Dependent>
                </ReferentialConstraint>
            </Association>
            <Association Name="to_header" sap:content-version="1">
                <End Type="cds_xsmyxpatient_ov_sdef.SAP__DocumentDescription" Multiplicity="1" Role="FromRole_to_header"/>
                <End Type="cds_xsmyxpatient_ov_sdef.SAP__PDFHeader" Multiplicity="1" Role="ToRole_to_header"/>
                <ReferentialConstraint>
                    <Principal Role="FromRole_to_header">
                        <PropertyRef Name="Id"/>
                    </Principal>
                    <Dependent Role="ToRole_to_header">
                        <PropertyRef Name="Id"/>
                    </Dependent>
                </ReferentialConstraint>
            </Association>
            <Association Name="to_Footer" sap:content-version="1">
                <End Type="cds_xsmyxpatient_ov_sdef.SAP__DocumentDescription" Multiplicity="1" Role="FromRole_to_Footer"/>
                <End Type="cds_xsmyxpatient_ov_sdef.SAP__PDFFooter" Multiplicity="1" Role="ToRole_to_Footer"/>
                <ReferentialConstraint>
                    <Principal Role="FromRole_to_Footer">
                        <PropertyRef Name="Id"/>
                    </Principal>
                    <Dependent Role="ToRole_to_Footer">
                        <PropertyRef Name="Id"/>
                    </Dependent>
                </ReferentialConstraint>
            </Association>
            <Association Name="assoc_EFA97A370DEF41CC75A0D63A288559AF" sap:content-version="1">
                <End Type="cds_xsmyxpatient_ov_sdef.xSMYxC_ENCOUNTER_OVType" Multiplicity="1" Role="FromRole_assoc_EFA97A370DEF41CC75A0D63A288559AF"/>
                <End Type="cds_xsmyxpatient_ov_sdef.xSMYxC_CASE_OVType" Multiplicity="0..1" Role="ToRole_assoc_EFA97A370DEF41CC75A0D63A288559AF"/>
                <ReferentialConstraint>
                    <Principal Role="ToRole_assoc_EFA97A370DEF41CC75A0D63A288559AF">
                        <PropertyRef Name="CaseUUID"/>
                    </Principal>
                    <Dependent Role="FromRole_assoc_EFA97A370DEF41CC75A0D63A288559AF">
                        <PropertyRef Name="CaseUUID"/>
                    </Dependent>
                </ReferentialConstraint>
            </Association>
            <Association Name="assoc_F75C82D5E58129306E7348D48D16160E" sap:content-version="1">
                <End Type="cds_xsmyxpatient_ov_sdef.xSMYxC_CASE_OVType" Multiplicity="1" Role="FromRole_assoc_F75C82D5E58129306E7348D48D16160E"/>
                <End Type="cds_xsmyxpatient_ov_sdef.xSMYxC_PATIENT_OVType" Multiplicity="*" Role="ToRole_assoc_F75C82D5E58129306E7348D48D16160E"/>
            </Association>
            <Association Name="assoc_0D98C2FA7528CA7C3FA6A6250EF6821D" sap:content-version="1">
                <End Type="cds_xsmyxpatient_ov_sdef.xSMYxC_CASE_OVType" Multiplicity="1" Role="FromRole_assoc_0D98C2FA7528CA7C3FA6A6250EF6821D"/>
                <End Type="cds_xsmyxpatient_ov_sdef.xSMYxC_ENCOUNTER_OVType" Multiplicity="*" Role="ToRole_assoc_0D98C2FA7528CA7C3FA6A6250EF6821D"/>
            </Association>
            <EntityContainer Name="cds_xsmyxpatient_ov_sdef_Entities" m:IsDefaultEntityContainer="true" sap:message-scope-supported="true" sap:supported-formats="atom json xlsx pdf">
                <EntitySet Name="SAP__Currencies" EntityType="cds_xsmyxpatient_ov_sdef.SAP__Currency" sap:content-version="1"/>
                <EntitySet Name="SAP__UnitsOfMeasure" EntityType="cds_xsmyxpatient_ov_sdef.SAP__UnitOfMeasure" sap:content-version="1"/>
                <EntitySet Name="SAP__MyDocumentDescriptions" EntityType="cds_xsmyxpatient_ov_sdef.SAP__DocumentDescription" sap:content-version="1"/>
                <EntitySet Name="SAP__FormatSet" EntityType="cds_xsmyxpatient_ov_sdef.SAP__Format" sap:creatable="false" sap:updatable="false" sap:deletable="false" sap:pageable="false" sap:addressable="false" sap:content-version="1"/>
                <EntitySet Name="SAP__PDFStandardSet" EntityType="cds_xsmyxpatient_ov_sdef.SAP__PDFStandard" sap:creatable="false" sap:updatable="false" sap:deletable="false" sap:pageable="false" sap:addressable="false" sap:content-version="1"/>
                <EntitySet Name="SAP__TableColumnsSet" EntityType="cds_xsmyxpatient_ov_sdef.SAP__TableColumns" sap:creatable="false" sap:updatable="false" sap:deletable="false" sap:pageable="false" sap:addressable="false" sap:content-version="1"/>
                <EntitySet Name="SAP__CoverPageSet" EntityType="cds_xsmyxpatient_ov_sdef.SAP__CoverPage" sap:creatable="false" sap:updatable="false" sap:deletable="false" sap:pageable="false" sap:addressable="false" sap:content-version="1"/>
                <EntitySet Name="SAP__SignatureSet" EntityType="cds_xsmyxpatient_ov_sdef.SAP__Signature" sap:creatable="false" sap:updatable="false" sap:deletable="false" sap:pageable="false" sap:addressable="false" sap:content-version="1"/>
                <EntitySet Name="SAP__HierarchySet" EntityType="cds_xsmyxpatient_ov_sdef.SAP__Hierarchy" sap:creatable="false" sap:updatable="false" sap:deletable="false" sap:pageable="false" sap:addressable="false" sap:content-version="1"/>
                <EntitySet Name="SAP__PDFHeaderSet" EntityType="cds_xsmyxpatient_ov_sdef.SAP__PDFHeader" sap:creatable="false" sap:updatable="false" sap:deletable="false" sap:pageable="false" sap:addressable="false" sap:content-version="1"/>
                <EntitySet Name="SAP__PDFFooterSet" EntityType="cds_xsmyxpatient_ov_sdef.SAP__PDFFooter" sap:creatable="false" sap:updatable="false" sap:deletable="false" sap:pageable="false" sap:addressable="false" sap:content-version="1"/>
                <EntitySet Name="SAP__ValueHelpSet" EntityType="cds_xsmyxpatient_ov_sdef.SAP__ValueHelp" sap:content-version="1"/>
                <EntitySet Name="xSMYxC_CASE_OV" EntityType="cds_xsmyxpatient_ov_sdef.xSMYxC_CASE_OVType" sap:creatable="false" sap:updatable="false" sap:deletable="false" sap:content-version="1"/>
                <EntitySet Name="xSMYxC_ENCOUNTER_OV" EntityType="cds_xsmyxpatient_ov_sdef.xSMYxC_ENCOUNTER_OVType" sap:creatable="false" sap:updatable="false" sap:deletable="false" sap:content-version="1"/>
                <EntitySet Name="xSMYxC_PATIENT_OV" EntityType="cds_xsmyxpatient_ov_sdef.xSMYxC_PATIENT_OVType" sap:creatable="false" sap:deletable="false" sap:content-version="1" sap:updatable-path="Update_mc"/>
                <AssociationSet Name="to_FooterSet" Association="cds_xsmyxpatient_ov_sdef.to_Footer" sap:creatable="false" sap:updatable="false" sap:deletable="false" sap:content-version="1">
                    <End EntitySet="SAP__MyDocumentDescriptions" Role="FromRole_to_Footer"/>
                    <End EntitySet="SAP__PDFFooterSet" Role="ToRole_to_Footer"/>
                </AssociationSet>
                <AssociationSet Name="to_headerSet" Association="cds_xsmyxpatient_ov_sdef.to_header" sap:creatable="false" sap:updatable="false" sap:deletable="false" sap:content-version="1">
                    <End EntitySet="SAP__MyDocumentDescriptions" Role="FromRole_to_header"/>
                    <End EntitySet="SAP__PDFHeaderSet" Role="ToRole_to_header"/>
                </AssociationSet>
                <AssociationSet Name="assoc_45353E7458BEC3091C0CB247DFD6E58E" Association="cds_xsmyxpatient_ov_sdef.assoc_45353E7458BEC3091C0CB247DFD6E58E" sap:creatable="false" sap:updatable="false" sap:deletable="false" sap:content-version="1">
                    <End EntitySet="xSMYxC_PATIENT_OV" Role="FromRole_assoc_45353E7458BEC3091C0CB247DFD6E58E"/>
                    <End EntitySet="xSMYxC_ENCOUNTER_OV" Role="ToRole_assoc_45353E7458BEC3091C0CB247DFD6E58E"/>
                </AssociationSet>
                <AssociationSet Name="to_formatSet" Association="cds_xsmyxpatient_ov_sdef.to_format" sap:creatable="false" sap:updatable="false" sap:deletable="false" sap:content-version="1">
                    <End EntitySet="SAP__MyDocumentDescriptions" Role="FromRole_to_format"/>
                    <End EntitySet="SAP__FormatSet" Role="ToRole_to_format"/>
                </AssociationSet>
                <AssociationSet Name="to_pdfstandardSet" Association="cds_xsmyxpatient_ov_sdef.to_pdfstandard" sap:creatable="false" sap:updatable="false" sap:deletable="false" sap:content-version="1">
                    <End EntitySet="SAP__MyDocumentDescriptions" Role="FromRole_to_pdfstandard"/>
                    <End EntitySet="SAP__PDFStandardSet" Role="ToRole_to_pdfstandard"/>
                </AssociationSet>
                <AssociationSet Name="assoc_EFA97A370DEF41CC75A0D63A288559AF" Association="cds_xsmyxpatient_ov_sdef.assoc_EFA97A370DEF41CC75A0D63A288559AF" sap:creatable="false" sap:updatable="false" sap:deletable="false" sap:content-version="1">
                    <End EntitySet="xSMYxC_ENCOUNTER_OV" Role="FromRole_assoc_EFA97A370DEF41CC75A0D63A288559AF"/>
                    <End EntitySet="xSMYxC_CASE_OV" Role="ToRole_assoc_EFA97A370DEF41CC75A0D63A288559AF"/>
                </AssociationSet>
                <AssociationSet Name="to_tablecolumnsSet" Association="cds_xsmyxpatient_ov_sdef.to_tablecolumns" sap:creatable="false" sap:updatable="false" sap:deletable="false" sap:content-version="1">
                    <End EntitySet="SAP__MyDocumentDescriptions" Role="FromRole_to_tablecolumns"/>
                    <End EntitySet="SAP__TableColumnsSet" Role="ToRole_to_tablecolumns"/>
                </AssociationSet>
                <AssociationSet Name="to_signatureSet" Association="cds_xsmyxpatient_ov_sdef.to_signature" sap:creatable="false" sap:updatable="false" sap:deletable="false" sap:content-version="1">
                    <End EntitySet="SAP__MyDocumentDescriptions" Role="FromRole_to_signature"/>
                    <End EntitySet="SAP__SignatureSet" Role="ToRole_to_signature"/>
                </AssociationSet>
                <AssociationSet Name="assoc_F1133A265B568B0CA18E38A117B7F811" Association="cds_xsmyxpatient_ov_sdef.assoc_F1133A265B568B0CA18E38A117B7F811" sap:creatable="false" sap:updatable="false" sap:deletable="false" sap:content-version="1">
                    <End EntitySet="xSMYxC_PATIENT_OV" Role="FromRole_assoc_F1133A265B568B0CA18E38A117B7F811"/>
                    <End EntitySet="xSMYxC_CASE_OV" Role="ToRole_assoc_F1133A265B568B0CA18E38A117B7F811"/>
                </AssociationSet>
                <AssociationSet Name="to_coverpageSet" Association="cds_xsmyxpatient_ov_sdef.to_coverpage" sap:creatable="false" sap:updatable="false" sap:deletable="false" sap:content-version="1">
                    <End EntitySet="SAP__MyDocumentDescriptions" Role="FromRole_to_coverpage"/>
                    <End EntitySet="SAP__CoverPageSet" Role="ToRole_to_coverpage"/>
                </AssociationSet>
                <AssociationSet Name="assoc_0D98C2FA7528CA7C3FA6A6250EF6821D" Association="cds_xsmyxpatient_ov_sdef.assoc_0D98C2FA7528CA7C3FA6A6250EF6821D" sap:creatable="false" sap:updatable="false" sap:deletable="false" sap:content-version="1">
                    <End EntitySet="xSMYxC_CASE_OV" Role="FromRole_assoc_0D98C2FA7528CA7C3FA6A6250EF6821D"/>
                    <End EntitySet="xSMYxC_ENCOUNTER_OV" Role="ToRole_assoc_0D98C2FA7528CA7C3FA6A6250EF6821D"/>
                </AssociationSet>
                <AssociationSet Name="to_HierarchySet" Association="cds_xsmyxpatient_ov_sdef.to_Hierarchy" sap:creatable="false" sap:updatable="false" sap:deletable="false" sap:content-version="1">
                    <End EntitySet="SAP__MyDocumentDescriptions" Role="FromRole_to_Hierarchy"/>
                    <End EntitySet="SAP__HierarchySet" Role="ToRole_to_Hierarchy"/>
                </AssociationSet>
                <AssociationSet Name="assoc_F75C82D5E58129306E7348D48D16160E" Association="cds_xsmyxpatient_ov_sdef.assoc_F75C82D5E58129306E7348D48D16160E" sap:creatable="false" sap:updatable="false" sap:deletable="false" sap:content-version="1">
                    <End EntitySet="xSMYxC_CASE_OV" Role="FromRole_assoc_F75C82D5E58129306E7348D48D16160E"/>
                    <End EntitySet="xSMYxC_PATIENT_OV" Role="ToRole_assoc_F75C82D5E58129306E7348D48D16160E"/>
                </AssociationSet>
            </EntityContainer>
            <Annotation Term="Core.SchemaVersion" String="1.0.0" xmlns="http://docs.oasis-open.org/odata/ns/edm"/>
            <Annotations Target="cds_xsmyxpatient_ov_sdef.cds_xsmyxpatient_ov_sdef_Entities" xmlns="http://docs.oasis-open.org/odata/ns/edm">
                <Annotation Term="Common.ApplyMultiUnitBehaviorForSortingAndFiltering" Bool="true"/>
            </Annotations>
            <Annotations Target="cds_xsmyxpatient_ov_sdef.xSMYxC_ENCOUNTER_OVType/EncStart" xmlns="http://docs.oasis-open.org/odata/ns/edm">
                <Annotation Term="Measures.DurationGranularity" String="days"/>
                <Annotation Term="Common.FieldControl" EnumMember="Common.FieldControlType/Mandatory"/>
            </Annotations>
            <Annotations Target="cds_xsmyxpatient_ov_sdef.xSMYxC_CASE_OVType/CaseCat" xmlns="http://docs.oasis-open.org/odata/ns/edm">
                <Annotation Term="Common.FieldControl" EnumMember="Common.FieldControlType/Mandatory"/>
            </Annotations>
            <Annotations Target="cds_xsmyxpatient_ov_sdef.xSMYxC_CASE_OVType/CaseStart" xmlns="http://docs.oasis-open.org/odata/ns/edm">
                <Annotation Term="Common.FieldControl" EnumMember="Common.FieldControlType/Mandatory"/>
            </Annotations>
            <Annotations Target="cds_xsmyxpatient_ov_sdef.xSMYxC_CASE_OVType/CaseStatus" xmlns="http://docs.oasis-open.org/odata/ns/edm">
                <Annotation Term="Common.FieldControl" EnumMember="Common.FieldControlType/Mandatory"/>
            </Annotations>
            <Annotations Target="cds_xsmyxpatient_ov_sdef.xSMYxC_CASE_OVType/CaseType" xmlns="http://docs.oasis-open.org/odata/ns/edm">
                <Annotation Term="Common.FieldControl" EnumMember="Common.FieldControlType/Mandatory"/>
            </Annotations>
            <Annotations Target="cds_xsmyxpatient_ov_sdef.xSMYxC_ENCOUNTER_OVType/EncClass" xmlns="http://docs.oasis-open.org/odata/ns/edm">
                <Annotation Term="Common.FieldControl" EnumMember="Common.FieldControlType/Mandatory"/>
            </Annotations>
            <Annotations Target="cds_xsmyxpatient_ov_sdef.xSMYxC_ENCOUNTER_OVType/EncPrio" xmlns="http://docs.oasis-open.org/odata/ns/edm">
                <Annotation Term="Common.FieldControl" EnumMember="Common.FieldControlType/Mandatory"/>
            </Annotations>
            <Annotations Target="cds_xsmyxpatient_ov_sdef.xSMYxC_ENCOUNTER_OVType/EncStatus" xmlns="http://docs.oasis-open.org/odata/ns/edm">
                <Annotation Term="Common.FieldControl" EnumMember="Common.FieldControlType/Mandatory"/>
            </Annotations>
            <Annotations Target="cds_xsmyxpatient_ov_sdef.xSMYxC_ENCOUNTER_OVType/EncType" xmlns="http://docs.oasis-open.org/odata/ns/edm">
                <Annotation Term="Common.FieldControl" EnumMember="Common.FieldControlType/Mandatory"/>
            </Annotations>
            <Annotations Target="cds_xsmyxpatient_ov_sdef.cds_xsmyxpatient_ov_sdef_Entities/xSMYxC_PATIENT_OV" xmlns="http://docs.oasis-open.org/odata/ns/edm">
                <Annotation Term="Capabilities.FilterRestrictions">
                    <Record>
                        <PropertyValue Property="NonFilterableProperties">
                            <Collection>
                                <PropertyPath>Update_mc</PropertyPath>
                            </Collection>
                        </PropertyValue>
                    </Record>
                </Annotation>
                <Annotation Term="Capabilities.NavigationRestrictions">
                    <Record>
                        <PropertyValue Property="RestrictedProperties">
                            <Collection>
                                <Record>
                                    <PropertyValue Property="NavigationProperty" NavigationPropertyPath="to_Case"/>
                                    <PropertyValue Property="InsertRestrictions">
                                        <Record>
                                            <PropertyValue Property="Insertable" Bool="false"/>
                                        </Record>
                                    </PropertyValue>
                                </Record>
                                <Record>
                                    <PropertyValue Property="NavigationProperty" NavigationPropertyPath="to_Encounter"/>
                                    <PropertyValue Property="InsertRestrictions">
                                        <Record>
                                            <PropertyValue Property="Insertable" Bool="false"/>
                                        </Record>
                                    </PropertyValue>
                                </Record>
                            </Collection>
                        </PropertyValue>
                    </Record>
                </Annotation>
                <Annotation Term="SAP__core.OptimisticConcurrency">
                    <Collection/>
                </Annotation>
                <Annotation Term="Capabilities.SortRestrictions">
                    <Record>
                        <PropertyValue Property="NonSortableProperties">
                            <Collection>
                                <PropertyPath>Update_mc</PropertyPath>
                            </Collection>
                        </PropertyValue>
                    </Record>
                </Annotation>
            </Annotations>
            <Annotations Target="cds_xsmyxpatient_ov_sdef.xSMYxC_CASE_OVType/Org" xmlns="http://docs.oasis-open.org/odata/ns/edm">
                <Annotation Term="SAP__core.Immutable"/>
            </Annotations>
            <Annotations Target="cds_xsmyxpatient_ov_sdef.xSMYxC_CASE_OVType/PatientUuid" xmlns="http://docs.oasis-open.org/odata/ns/edm">
                <Annotation Term="SAP__core.Immutable"/>
            </Annotations>
            <Annotations Target="cds_xsmyxpatient_ov_sdef.xSMYxC_ENCOUNTER_OVType/CaseUUID" xmlns="http://docs.oasis-open.org/odata/ns/edm">
                <Annotation Term="SAP__core.Immutable"/>
            </Annotations>
            <Annotations Target="cds_xsmyxpatient_ov_sdef.xSMYxC_PATIENT_OVType/PatientUUID" xmlns="http://docs.oasis-open.org/odata/ns/edm">
                <Annotation Term="SAP__core.Immutable"/>
            </Annotations>
            <Annotations Target="cds_xsmyxpatient_ov_sdef.cds_xsmyxpatient_ov_sdef_Entities/xSMYxC_CASE_OV" xmlns="http://docs.oasis-open.org/odata/ns/edm">
                <Annotation Term="Capabilities.InsertRestrictions">
                    <Record>
                        <PropertyValue Property="RequiredProperties">
                            <Collection>
                                <PropertyPath>PatientUuid</PropertyPath>
                                <PropertyPath>Org</PropertyPath>
                            </Collection>
                        </PropertyValue>
                    </Record>
                </Annotation>
                <Annotation Term="Capabilities.NavigationRestrictions">
                    <Record>
                        <PropertyValue Property="RestrictedProperties">
                            <Collection>
                                <Record>
                                    <PropertyValue Property="NavigationProperty" NavigationPropertyPath="to_Encounter"/>
                                    <PropertyValue Property="InsertRestrictions">
                                        <Record>
                                            <PropertyValue Property="Insertable" Bool="false"/>
                                        </Record>
                                    </PropertyValue>
                                </Record>
                                <Record>
                                    <PropertyValue Property="NavigationProperty" NavigationPropertyPath="to_Patient"/>
                                    <PropertyValue Property="InsertRestrictions">
                                        <Record>
                                            <PropertyValue Property="Insertable" Bool="false"/>
                                        </Record>
                                    </PropertyValue>
                                </Record>
                            </Collection>
                        </PropertyValue>
                    </Record>
                </Annotation>
                <Annotation Term="SAP__core.OptimisticConcurrency">
                    <Collection/>
                </Annotation>
            </Annotations>
            <Annotations Target="cds_xsmyxpatient_ov_sdef.cds_xsmyxpatient_ov_sdef_Entities/xSMYxC_ENCOUNTER_OV" xmlns="http://docs.oasis-open.org/odata/ns/edm">
                <Annotation Term="Capabilities.InsertRestrictions">
                    <Record>
                        <PropertyValue Property="RequiredProperties">
                            <Collection>
                                <PropertyPath>CaseUUID</PropertyPath>
                            </Collection>
                        </PropertyValue>
                    </Record>
                </Annotation>
                <Annotation Term="Capabilities.NavigationRestrictions">
                    <Record>
                        <PropertyValue Property="RestrictedProperties">
                            <Collection>
                                <Record>
                                    <PropertyValue Property="NavigationProperty" NavigationPropertyPath="to_EpisodeOfCare"/>
                                    <PropertyValue Property="InsertRestrictions">
                                        <Record>
                                            <PropertyValue Property="Insertable" Bool="false"/>
                                        </Record>
                                    </PropertyValue>
                                </Record>
                            </Collection>
                        </PropertyValue>
                    </Record>
                </Annotation>
                <Annotation Term="SAP__core.OptimisticConcurrency">
                    <Collection/>
                </Annotation>
            </Annotations>
            <Annotations Target="cds_xsmyxpatient_ov_sdef.xSMYxC_CASE_OVType" xmlns="http://docs.oasis-open.org/odata/ns/edm">
                <Annotation Term="Common.SemanticKey">
                    <Collection>
                        <PropertyPath>CaseUUID</PropertyPath>
                    </Collection>
                </Annotation>
            </Annotations>
            <Annotations Target="cds_xsmyxpatient_ov_sdef.cds_xsmyxpatient_ov_sdef_Entities" xmlns="http://docs.oasis-open.org/odata/ns/edm">
                <Annotation Term="Org.OData.Capabilities.V1.BatchSupport">
                    <Record Type="Org.OData.Capabilities.V1.BatchSupportType">
                        <PropertyValue Property="ReferencesAcrossChangeSetsSupported" Bool="true"/>
                    </Record>
                </Annotation>
                <Annotation Term="SAP__CodeList.CurrencyCodes">
                    <Record>
                        <PropertyValue Property="Url" String="./$metadata"/>
                        <PropertyValue Property="CollectionPath" String="SAP__Currencies"/>
                    </Record>
                </Annotation>
                <Annotation Term="SAP__CodeList.UnitsOfMeasure">
                    <Record>
                        <PropertyValue Property="Url" String="./$metadata"/>
                        <PropertyValue Property="CollectionPath" String="SAP__UnitsOfMeasure"/>
                    </Record>
                </Annotation>
                <Annotation Term="SAP__PDF.Features">
                    <Record>
                        <PropertyValue Property="DocumentDescriptionReference" String="./$metadata"/>
                        <PropertyValue Property="DocumentDescriptionCollection" String="SAP__MyDocumentDescriptions"/>
                        <PropertyValue Property="ArchiveFormat" Bool="true"/>
                        <PropertyValue Property="CoverPage" Bool="true"/>
                        <PropertyValue Property="Signature" Bool="true"/>
                        <PropertyValue Property="FitToPage" Bool="true"/>
                        <PropertyValue Property="FontName" Bool="true"/>
                        <PropertyValue Property="FontSize" Bool="true"/>
                        <PropertyValue Property="Margin" Bool="true"/>
                        <PropertyValue Property="Border" Bool="true"/>
                        <PropertyValue Property="Padding" Bool="true"/>
                        <PropertyValue Property="HeaderFooter" Bool="true"/>
                        <PropertyValue Property="ResultSizeDefault" Int="20000"/>
                        <PropertyValue Property="ResultSizeMaximum" Int="20000"/>
                    </Record>
                </Annotation>
                <Annotation Term="SAP__CodeList.SAP__DocumentDescription">
                    <Record>
                        <PropertyValue Property="Url" String="./$metadata"/>
                        <PropertyValue Property="CollectionPath" String="SAP__MyDocumentDescriptions"/>
                    </Record>
                </Annotation>
            </Annotations>
            <Annotations Target="cds_xsmyxpatient_ov_sdef.SAP__Currency/CurrencyCode" xmlns="http://docs.oasis-open.org/odata/ns/edm">
                <Annotation Term="SAP__common.Text" Path="Text"/>
                <Annotation Term="SAP__common.UnitSpecificScale" Path="DecimalPlaces"/>
                <Annotation Term="SAP__CodeList.StandardCode" Path="ISOCode"/>
            </Annotations>
            <Annotations Target="cds_xsmyxpatient_ov_sdef.SAP__UnitOfMeasure/UnitCode" xmlns="http://docs.oasis-open.org/odata/ns/edm">
                <Annotation Term="SAP__common.Text" Path="Text"/>
                <Annotation Term="SAP__common.UnitSpecificScale" Path="DecimalPlaces"/>
                <Annotation Term="SAP__CodeList.StandardCode" Path="ISOCode"/>
                <Annotation Term="SAP__CodeList.ExternalCode" Path="ExternalCode"/>
            </Annotations>
            <Annotations Target="cds_xsmyxpatient_ov_sdef.SAP__UnitOfMeasure" xmlns="http://docs.oasis-open.org/odata/ns/edm">
                <Annotation Term="SAP__core.AlternateKeys">
                    <Collection>
                        <Record>
                            <PropertyValue Property="Key">
                                <Collection>
                                    <Record>
                                        <PropertyValue Property="Name" Path="ExternalCode"/>
                                        <PropertyValue Property="Alias" String="ExternalCode"/>
                                    </Record>
                                </Collection>
                            </PropertyValue>
                        </Record>
                    </Collection>
                </Annotation>
            </Annotations>
            <Annotations Target="cds_xsmyxpatient_ov_sdef.SAP__DocumentDescription/CreatedBy" xmlns="http://docs.oasis-open.org/odata/ns/edm">
                <Annotation Term="SAP__core.Computed"/>
            </Annotations>
            <Annotations Target="cds_xsmyxpatient_ov_sdef.SAP__DocumentDescription/CreatedAt" xmlns="http://docs.oasis-open.org/odata/ns/edm">
                <Annotation Term="SAP__core.Computed"/>
            </Annotations>
            <Annotations Target="cds_xsmyxpatient_ov_sdef.SAP__DocumentDescription" xmlns="http://docs.oasis-open.org/odata/ns/edm">
                <Annotation Term="SAP__capabilties.InsertRestrictions">
                    <Record>
                        <PropertyValue Property="Insertable" Bool="false"/>
                    </Record>
                </Annotation>
                <Annotation Term="SAP__capabilties.UpdateRestrictions">
                    <Record>
                        <PropertyValue Property="Updatable" Bool="false"/>
                        <PropertyValue Property="QueryOptions">
                            <Record>
                                <PropertyValue Property="SelectSupported" Bool="true"/>
                            </Record>
                        </PropertyValue>
                    </Record>
                </Annotation>
                <Annotation Term="SAP__capabilties.DeleteRestrictions">
                    <Record>
                        <PropertyValue Property="Deletable" Bool="false"/>
                    </Record>
                </Annotation>
                <Annotation Term="SAP__capabilties.FilterRestrictions">
                    <Record>
                        <PropertyValue Property="FilterExpressionRestrictions">
                            <Collection>
                                <Record>
                                    <PropertyValue Property="Property" PropertyPath="Format/Orientation"/>
                                    <PropertyValue Property="AllowedExpressions" String="Multivalue"/>
                                </Record>
                                <Record>
                                    <PropertyValue Property="Property" PropertyPath="Format/PaperSize"/>
                                    <PropertyValue Property="AllowedExpressions" String="Multivalue"/>
                                </Record>
                            </Collection>
                        </PropertyValue>
                    </Record>
                </Annotation>
            </Annotations>
            <Annotations Target="cds_xsmyxpatient_ov_sdef.SAP__Format/FitToPage/ErrorRecoveryBehavior" xmlns="http://docs.oasis-open.org/odata/ns/edm">
                <Annotation Term="SAP__common.ValueListReferences">
                    <Record>
                        <PropertyValue Property="Url" String="./$metadata"/>
                        <PropertyValue Property="CollectionPath" String="../../../../SAP__ValueHelpSet?$filter=VALUEHELP%20eq%20%27ErrorRecoveryBehaviour%27"/>
                    </Record>
                </Annotation>
                <Annotation Term="SAP__common.ValueListWithFixedValues"/>
            </Annotations>
            <Annotations Target="cds_xsmyxpatient_ov_sdef.SAP__Format/FontName" xmlns="http://docs.oasis-open.org/odata/ns/edm">
                <Annotation Term="SAP__common.ValueListReferences">
                    <Record>
                        <PropertyValue Property="Url" String="./$metadata"/>
                        <PropertyValue Property="CollectionPath" String="SAP__ValueHelpSet?$filter=VALUEHELP%20eq%20%27FontName%27"/>
                    </Record>
                </Annotation>
                <Annotation Term="SAP__common.ValueListWithFixedValues"/>
            </Annotations>
            <Annotations Target="cds_xsmyxpatient_ov_sdef.SAP__Format/PaperSize" xmlns="http://docs.oasis-open.org/odata/ns/edm">
                <Annotation Term="SAP__common.ValueListReferences">
                    <Record>
                        <PropertyValue Property="Url" String="./$metadata"/>
                        <PropertyValue Property="CollectionPath" String="SAP__ValueHelpSet?$filter=VALUEHELP%20eq%20%27PaperSize%27"/>
                    </Record>
                </Annotation>
                <Annotation Term="SAP__common.ValueListWithFixedValues"/>
            </Annotations>
            <Annotations Target="cds_xsmyxpatient_ov_sdef.SAP__PDFHeader/Left" xmlns="http://docs.oasis-open.org/odata/ns/edm">
                <Annotation Term="SAP__common.ValueListReferences">
                    <Record>
                        <PropertyValue Property="Url" String="./$metadata"/>
                        <PropertyValue Property="CollectionPath" String="SAP__ValueHelpSet?$filter=VALUEHELP%20eq%20%27HeaderFooter%27"/>
                    </Record>
                </Annotation>
                <Annotation Term="SAP__common.ValueListWithFixedValues"/>
            </Annotations>
            <Annotations Target="cds_xsmyxpatient_ov_sdef.SAP__PDFHeader/Right" xmlns="http://docs.oasis-open.org/odata/ns/edm">
                <Annotation Term="SAP__common.ValueListReferences">
                    <Record>
                        <PropertyValue Property="Url" String="./$metadata"/>
                        <PropertyValue Property="CollectionPath" String="SAP__ValueHelpSet?$filter=VALUEHELP%20eq%20%27HeaderFooter%27"/>
                    </Record>
                </Annotation>
                <Annotation Term="SAP__common.ValueListWithFixedValues"/>
            </Annotations>
            <Annotations Target="cds_xsmyxpatient_ov_sdef.SAP__PDFHeader/Center" xmlns="http://docs.oasis-open.org/odata/ns/edm">
                <Annotation Term="SAP__common.ValueListReferences">
                    <Record>
                        <PropertyValue Property="Url" String="./$metadata"/>
                        <PropertyValue Property="CollectionPath" String="SAP__ValueHelpSet?$filter=VALUEHELP%20eq%20%27HeaderFooter%27"/>
                    </Record>
                </Annotation>
                <Annotation Term="SAP__common.ValueListWithFixedValues"/>
            </Annotations>
            <Annotations Target="cds_xsmyxpatient_ov_sdef.SAP__PDFFooter/Left" xmlns="http://docs.oasis-open.org/odata/ns/edm">
                <Annotation Term="SAP__common.ValueListReferences">
                    <Record>
                        <PropertyValue Property="Url" String="./$metadata"/>
                        <PropertyValue Property="CollectionPath" String="SAP__ValueHelpSet?$filter=VALUEHELP%20eq%20%27HeaderFooter%27"/>
                    </Record>
                </Annotation>
                <Annotation Term="SAP__common.ValueListWithFixedValues"/>
            </Annotations>
            <Annotations Target="cds_xsmyxpatient_ov_sdef.SAP__PDFFooter/Right" xmlns="http://docs.oasis-open.org/odata/ns/edm">
                <Annotation Term="SAP__common.ValueListReferences">
                    <Record>
                        <PropertyValue Property="Url" String="./$metadata"/>
                        <PropertyValue Property="CollectionPath" String="SAP__ValueHelpSet?$filter=VALUEHELP%20eq%20%27HeaderFooter%27"/>
                    </Record>
                </Annotation>
                <Annotation Term="SAP__common.ValueListWithFixedValues"/>
            </Annotations>
            <Annotations Target="cds_xsmyxpatient_ov_sdef.SAP__PDFFooter/Center" xmlns="http://docs.oasis-open.org/odata/ns/edm">
                <Annotation Term="SAP__common.ValueListReferences">
                    <Record>
                        <PropertyValue Property="Url" String="./$metadata"/>
                        <PropertyValue Property="CollectionPath" String="SAP__ValueHelpSet?$filter=VALUEHELP%20eq%20%27HeaderFooter%27"/>
                    </Record>
                </Annotation>
                <Annotation Term="SAP__common.ValueListWithFixedValues"/>
            </Annotations>
            <Annotations Target="cds_xsmyxpatient_ov_sdef.SAP__Format/Orientation" xmlns="http://docs.oasis-open.org/odata/ns/edm">
                <Annotation Term="SAP__common.ValueListReferences">
                    <Record>
                        <PropertyValue Property="Url" String="./$metadata"/>
                        <PropertyValue Property="CollectionPath" String="SAP__ValueHelpSet?$filter=VALUEHELP%20eq%20%27FontName%27"/>
                    </Record>
                </Annotation>
                <Annotation Term="SAP__common.ValueListWithFixedValues"/>
            </Annotations>
            <Annotations Target="cds_xsmyxpatient_ov_sdef.SAP__TableColumns/HorizontalAlignment" xmlns="http://docs.oasis-open.org/odata/ns/edm">
                <Annotation Term="SAP__common.ValueListReferences">
                    <Record>
                        <PropertyValue Property="Url" String="./$metadata"/>
                        <PropertyValue Property="CollectionPath" String="SAP__ValueHelpSet?$filter=VALUEHELP%20eq%20%27HorizontalAlignment%27"/>
                    </Record>
                </Annotation>
                <Annotation Term="SAP__common.ValueListWithFixedValues"/>
            </Annotations>
            <atom:link rel="self" href="http://192.168.3.113:8000/sap/opu/odata/smy/PATIENT_OV_FE/$metadata" xmlns:atom="http://www.w3.org/2005/Atom"/>
            <atom:link rel="latest-version" href="http://192.168.3.113:8000/sap/opu/odata/smy/PATIENT_OV_FE/$metadata" xmlns:atom="http://www.w3.org/2005/Atom"/>
        </Schema>
    </edmx:DataServices>
</edmx:Edmx>